AVOlibraryCP/__init__.py
AVOlibraryCP/modulo.py
AVOlibraryCP-0.5.dist-info/METADATA
AVOlibraryCP-0.5.dist-info/WHEEL
AVOlibraryCP-0.5.dist-info/top_level.txt
AVOlibraryCP-0.5.dist-info/RECORD
