Metadata-Version: 2.1
Name: AVOlibraryCP
Version: 0.5
Summary: Solve integral using the montecarlo method
Author: Alejandro Valencia
Author-email: alejandro.valenciao1@udea.edu.co
License: MIT
Requires-Dist: numpy
Requires-Dist: scipy
Requires-Dist: matplotlib
